cdk_vscode_fargate/__init__.py
cdk_vscode_fargate/py.typed
cdk_vscode_fargate/_jsii/__init__.py
cdk_vscode_fargate/_jsii/cdk-vscode-fargate@0.0.43.jsii.tgz
cdk_vscode_fargate-0.0.43.dist-info/LICENSE
cdk_vscode_fargate-0.0.43.dist-info/METADATA
cdk_vscode_fargate-0.0.43.dist-info/WHEEL
cdk_vscode_fargate-0.0.43.dist-info/top_level.txt
cdk_vscode_fargate-0.0.43.dist-info/RECORD
