Metadata-Version: 2.1
Name: cdk-vscode-fargate
Version: 0.0.43
Summary: cdk-vscode-fargate
Home-page: https://github.com/mikeapted/cdk-vscode-fargate.git
Author: Mike Apted<mike.apted@gmail.com>
License: Apache-2.0
Project-URL: Source, https://github.com/mikeapted/cdk-vscode-fargate.git
Platform: UNKNOWN
Classifier: Intended Audience :: Developers
Classifier: Operating System :: OS Independent
Classifier: Programming Language :: JavaScript
Classifier: Programming Language :: Python :: 3 :: Only
Classifier: Programming Language :: Python :: 3.6
Classifier: Programming Language :: Python :: 3.7
Classifier: Programming Language :: Python :: 3.8
Classifier: Programming Language :: Python :: 3.9
Classifier: Typing :: Typed
Classifier: Development Status :: 5 - Production/Stable
Classifier: License :: OSI Approved
Requires-Python: >=3.6
License-File: LICENSE
Requires-Dist: aws-cdk.aws-certificatemanager (<2.0.0,>=1.124.0)
Requires-Dist: aws-cdk.aws-ec2 (<2.0.0,>=1.124.0)
Requires-Dist: aws-cdk.aws-ecs-patterns (<2.0.0,>=1.124.0)
Requires-Dist: aws-cdk.aws-ecs (<2.0.0,>=1.124.0)
Requires-Dist: aws-cdk.aws-efs (<2.0.0,>=1.124.0)
Requires-Dist: aws-cdk.aws-kms (<2.0.0,>=1.124.0)
Requires-Dist: aws-cdk.aws-logs (<2.0.0,>=1.124.0)
Requires-Dist: aws-cdk.aws-route53 (<2.0.0,>=1.124.0)
Requires-Dist: aws-cdk.aws-secretsmanager (<2.0.0,>=1.124.0)
Requires-Dist: aws-cdk.core (<2.0.0,>=1.124.0)
Requires-Dist: constructs (<4.0.0,>=3.2.27)
Requires-Dist: jsii (<2.0.0,>=1.37.0)
Requires-Dist: publication (>=0.0.3)
